pluginTest/__init__.py
pluginTest/plugin.py
pluginTest-0.2.1.dist-info/METADATA
pluginTest-0.2.1.dist-info/WHEEL
pluginTest-0.2.1.dist-info/entry_points.txt
pluginTest-0.2.1.dist-info/top_level.txt
pluginTest-0.2.1.dist-info/RECORD
