Metadata-Version: 2.1
Name: pluginTest
Version: 0.2.1
Requires-Python: >=3.5
Requires-Dist: mkdocs
